GiantTour.py
giant_tour_class-1.5.dist-info/METADATA
giant_tour_class-1.5.dist-info/WHEEL
giant_tour_class-1.5.dist-info/top_level.txt
giant_tour_class-1.5.dist-info/RECORD
