Metadata-Version: 2.1
Name: giant-tour-class
Version: 1.5
Summary: giant tour class
Home-page: UNKNOWN
Author: Mr. Hanh
License: LICENSE.txt
Platform: UNKNOWN
Requires-Dist: ortools
Requires-Dist: kmedoids
